LICENSE
MANIFEST.in
README.md
requirements.txt
setup.py
xenny/__init__.py
xenny.egg-info/PKG-INFO
xenny.egg-info/SOURCES.txt
xenny.egg-info/dependency_links.txt
xenny.egg-info/requires.txt
xenny.egg-info/top_level.txt
xenny/ctf/__init__.py
xenny/ctf/crypto/__init__.py
xenny/ctf/crypto/classic/__init__.py
xenny/ctf/crypto/classic/multi/__init__.py
xenny/ctf/crypto/classic/multi/hill.py
xenny/ctf/crypto/classic/multi/playfair.py
xenny/ctf/crypto/classic/other/_01248.py
xenny/ctf/crypto/classic/other/__init__.py
xenny/ctf/crypto/classic/other/brainfuck.py
xenny/ctf/crypto/classic/single/__init__.py
xenny/ctf/crypto/classic/single/affine.py
xenny/ctf/crypto/classic/single/atbash.py
xenny/ctf/crypto/classic/single/caesar.py
xenny/ctf/crypto/classic/single/morse.py
xenny/ctf/crypto/classic/single/rot.py
xenny/ctf/crypto/classic/single/tap.py
xenny/ctf/crypto/hash/__init__.py
xenny/ctf/crypto/hash/utils.py
xenny/ctf/crypto/modern/__init__.py
xenny/ctf/crypto/modern/asymmetric/__init__.py
xenny/ctf/crypto/modern/asymmetric/dsa/__init__.py
xenny/ctf/crypto/modern/asymmetric/dsa/k_known.py
xenny/ctf/crypto/modern/asymmetric/dsa/k_share.py
xenny/ctf/crypto/modern/asymmetric/ecc/__init__.py
xenny/ctf/crypto/modern/asymmetric/ecc/ecc.py
xenny/ctf/crypto/modern/asymmetric/ecc/pohlig_hellman.sage
xenny/ctf/crypto/modern/asymmetric/ecc/pohlig_hellman.sage.py
xenny/ctf/crypto/modern/asymmetric/ecc/smart_attack.sage
xenny/ctf/crypto/modern/asymmetric/ecc/smart_attack.sage.py
xenny/ctf/crypto/modern/asymmetric/edrsa/__init__.py
xenny/ctf/crypto/modern/asymmetric/rsa/__init__.py
xenny/ctf/crypto/modern/asymmetric/rsa/amm.py
xenny/ctf/crypto/modern/asymmetric/rsa/dpleak.py
xenny/ctf/crypto/modern/asymmetric/rsa/factor.py
xenny/ctf/crypto/modern/asymmetric/rsa/lowe_broadcast.py
xenny/ctf/crypto/modern/asymmetric/rsa/pollard_p_1.py
xenny/ctf/crypto/modern/asymmetric/rsa/rabin.py
xenny/ctf/crypto/modern/asymmetric/rsa/rsa.py
xenny/ctf/crypto/modern/asymmetric/rsa/same_module.py
xenny/ctf/crypto/modern/asymmetric/rsa/schemidt_samoa.py
xenny/ctf/crypto/modern/asymmetric/rsa/small_plain.py
