Metadata-Version: 2.1
Name: xenny
Version: 1.4
Summary: Xenny's tool
Home-page: https://github.com/X3NNY/xenny
Author: X3NNY
Author-email: xennyxd1@gmail.com
License: MIT
Keywords: ctf,xenny,web,misc,crypto,reverse,pwn
Platform: UNKNOWN
Classifier: Intended Audience :: Developers
Classifier: License :: OSI Approved :: MIT License
Classifier: Natural Language :: English
Classifier: Programming Language :: Python :: 3.8
Classifier: Programming Language :: Python :: 3.9
Requires-Python: >=3.8.0
